{
    "app":  "TraceMQ",
    "channel":  "alpha",
    "version":  "0.4.0-alpha.6",
    "release_date":  "2025-12-23",
    "assets":  [
                   {
                       "url":  "https://github.com/Secureflow-SRL/tracemq-updates/releases/download/v0.4.0-alpha.6/TraceMQ_v0.4.0-alpha.6_windows_amd64.exe",
                       "arch":  "amd64",
                       "os":  "windows",
                       "hash":  "5c187041299a7d8acb3da6c7ad2d69789e740a9b8622f09216cb8979610083fd"
                   },
                   {
                       "url":  "https://github.com/Secureflow-SRL/tracemq-updates/releases/download/v0.4.0-alpha.6/TraceMQ_v0.4.0-alpha.6_linux_amd64",
                       "arch":  "amd64",
                       "os":  "linux",
                       "hash":  "54a3f161a880e8f2795540df22c96ad6bfd479494a297a6bd53bb13734bd6523"
                   }
               ]
}